<annotation verified="no">
  <folder>afbeelding brood</folder>
  <filename>Broodjes (44)</filename>
  <path>C:\Users\Jaime\Downloads\dataset 300x300\afbeelding brood\Broodjes (44).jpg</path>
  <source>
    <database>Unknown</database>
  </source>
  <size>
    <width>300</width>
    <height>300</height>
    <depth>3</depth>
  </size>
  <segmented>0</segmented>
  <object>
    <type>robndbox</type>
    <name>broodjes onderkant</name>
    <pose>Unspecified</pose>
    <truncated>0</truncated>
    <difficult>0</difficult>
    <robndbox>
      <cx>137.8038</cx>
      <cy>128.0</cy>
      <w>34.0</w>
      <h>66.0</h>
      <angle>0.0</angle>
    </robndbox>
  </object>
  <object>
    <type>robndbox</type>
    <name>broodjes onderkant</name>
    <pose>Unspecified</pose>
    <truncated>0</truncated>
    <difficult>0</difficult>
    <robndbox>
      <cx>172.7893</cx>
      <cy>131.4967</cy>
      <w>34.6541</w>
      <h>68.9212</h>
      <angle>0.23</angle>
    </robndbox>
  </object>
  <object>
    <type>robndbox</type>
    <name>broodjes onderkant</name>
    <pose>Unspecified</pose>
    <truncated>0</truncated>
    <difficult>0</difficult>
    <robndbox>
      <cx>200.7893</cx>
      <cy>205.4967</cy>
      <w>34.6541</w>
      <h>68.9212</h>
      <angle>0.07</angle>
    </robndbox>
  </object>
  <object>
    <type>robndbox</type>
    <name>broodjes bovenkant</name>
    <pose>Unspecified</pose>
    <truncated>0</truncated>
    <difficult>0</difficult>
    <robndbox>
      <cx>202.8038</cx>
      <cy>141.5</cy>
      <w>33.8902</w>
      <h>61.2899</h>
      <angle>0.25</angle>
    </robndbox>
  </object>
  <object>
    <type>robndbox</type>
    <name>broodjes bovenkant</name>
    <pose>Unspecified</pose>
    <truncated>0</truncated>
    <difficult>0</difficult>
    <robndbox>
      <cx>167.2161</cx>
      <cy>196.3335</cy>
      <w>36.9323</w>
      <h>62.516</h>
      <angle>0.15</angle>
    </robndbox>
  </object>
  <object>
    <type>robndbox</type>
    <name>broodjes bovenkant</name>
    <pose>Unspecified</pose>
    <truncated>0</truncated>
    <difficult>0</difficult>
    <robndbox>
      <cx>128.3947</cx>
      <cy>192.0752</cy>
      <w>35.9769</w>
      <h>66.2471</h>
      <angle>0.19</angle>
    </robndbox>
  </object>
  <object>
    <type>robndbox</type>
    <name>broodjes bovenkant</name>
    <pose>Unspecified</pose>
    <truncated>0</truncated>
    <difficult>0</difficult>
    <robndbox>
      <cx>152.0437</cx>
      <cy>241.5658</cy>
      <w>29.3532</w>
      <h>84.6224</h>
      <angle>1.761593</angle>
    </robndbox>
  </object>
</annotation>
